context_weave_ai_db/__init__.py
context_weave_ai_db/models.py
context_weave_ai_db/request_by_url_repo.py
context_weave_ai_db/request_repo.py
context_weave_ai_db/setup.py
context_weave_ai_db-0.0.3.dist-info/METADATA
context_weave_ai_db-0.0.3.dist-info/WHEEL
context_weave_ai_db-0.0.3.dist-info/top_level.txt
context_weave_ai_db-0.0.3.dist-info/RECORD
